winrt/_winrt_windows_ui_xaml_controls_primitives.cp310-win_amd64.pyd
winrt/_winrt_windows_ui_xaml_controls_primitives.pyi
winrt/_winrt_windows_ui_xaml_controls_primitives_2.cp310-win_amd64.pyd
winrt/_winrt_windows_ui_xaml_controls_primitives_2.pyi
winrt/windows/ui/xaml/controls/primitives/__init__.py
winrt/windows/ui/xaml/controls/primitives/py.typed
winrt_windows_ui_xaml_controls_primitives-3.2.1.dist-info/METADATA
winrt_windows_ui_xaml_controls_primitives-3.2.1.dist-info/WHEEL
winrt_windows_ui_xaml_controls_primitives-3.2.1.dist-info/top_level.txt
winrt_windows_ui_xaml_controls_primitives-3.2.1.dist-info/RECORD
